minetest_launcher/LauncherWindow.ui
minetest_launcher/PasswordEditor.ui
minetest_launcher/ServerList.ui
minetest_launcher/ServerWidget.ui
minetest_launcher/__init__.py
minetest_launcher/__main__.py
minetest_launcher/main.css
minetest_launcher-0.1.1.data/data/share/applications/io.github.destofr.MinetestLauncher.desktop
minetest_launcher-0.1.1.dist-info/COPYING
minetest_launcher-0.1.1.dist-info/METADATA
minetest_launcher-0.1.1.dist-info/WHEEL
minetest_launcher-0.1.1.dist-info/top_level.txt
minetest_launcher-0.1.1.dist-info/RECORD
